<?xml version="1.0" encoding="UTF-8"?>
<Students_Timetable>
  <Subgroup name="101 Grupo Automático Subgrupo Automático">
   <Day name="Luni">
    <Hour name="0">
      <Teacher name="Marli"></Teacher><Subject name="Historia"></Subject>
    </Hour>
    <Hour name="1">
      <Teacher name="Lima"></Teacher><Subject name="Fisica"></Subject>
    </Hour>
    <Hour name="2">
      <Teacher name="Carlos"></Teacher><Subject name="Quimica"></Subject>
    </Hour>
    <Hour name="3">
      <Teacher name="Maria da Luz"></Teacher><Subject name="Lingua Portuguesa"></Subject>
    </Hour>
    <Hour name="4">
      <Teacher name="Silvania"></Teacher><Subject name="Matematica"></Subject>
    </Hour>
   </Day>
   <Day name="Marti">
    <Hour name="0">
      <Teacher name="Lima"></Teacher><Subject name="Fisica"></Subject>
    </Hour>
    <Hour name="1">
      <Teacher name="Silvania"></Teacher><Subject name="Matematica"></Subject>
    </Hour>
    <Hour name="2">
      <Teacher name="Terezinha"></Teacher><Subject name="Geografia"></Subject>
    </Hour>
    <Hour name="3">
      <Teacher name="Giselle"></Teacher><Subject name="Biologia"></Subject>
    </Hour>
    <Hour name="4">
      <Teacher name="Carlos"></Teacher><Subject name="Quimica"></Subject>
    </Hour>
   </Day>
   <Day name="Miercuri">
    <Hour name="0">
      <Teacher name="Silvania"></Teacher><Subject name="Matematica"></Subject>
    </Hour>
    <Hour name="1">
      <Teacher name="Carlos"></Teacher><Subject name="Quimica"></Subject>
    </Hour>
    <Hour name="2">
      <Teacher name="Silvana"></Teacher><Subject name="Ingles"></Subject>
    </Hour>
    <Hour name="3">
      <Teacher name="Giselle"></Teacher><Subject name="Biologia"></Subject>
    </Hour>
    <Hour name="4">
      <Teacher name="Renata"></Teacher><Subject name="Educcacao Fisica"></Subject>
    </Hour>
   </Day>
   <Day name="Joi">
    <Hour name="0">
      <Teacher name="Maria da Luz"></Teacher><Subject name="Lingua Portuguesa"></Subject>
    </Hour>
    <Hour name="1">
      <Teacher name="Giselle"></Teacher><Subject name="Biologia"></Subject>
    </Hour>
    <Hour name="2">
      <Teacher name="Terezinha"></Teacher><Subject name="Geografia"></Subject>
    </Hour>
    <Hour name="3">
      <Teacher name="Marli"></Teacher><Subject name="Historia"></Subject>
    </Hour>
    <Hour name="4">
      <Teacher name="Gilmar"></Teacher><Subject name="Filosofia"></Subject>
    </Hour>
   </Day>
   <Day name="Vineri">
    <Hour name="0">
      <Teacher name="Maria da Luz"></Teacher><Subject name="Lingua Portuguesa"></Subject>
    </Hour>
    <Hour name="1">
      <Teacher name="Renata"></Teacher><Subject name="Educcacao Fisica"></Subject>
    </Hour>
    <Hour name="2">
      <Teacher name="Silvana"></Teacher><Subject name="Ingles"></Subject>
    </Hour>
    <Hour name="3">
      <Teacher name="Gilmar"></Teacher><Subject name="Filosofia"></Subject>
    </Hour>
    <Hour name="4">
      <Teacher name="Lima"></Teacher><Subject name="Fisica"></Subject>
    </Hour>
   </Day>
  </Subgroup>
  <Subgroup name="102 Grupo Automático Subgrupo Automático">
   <Day name="Luni">
    <Hour name="0">
      <Teacher name="Maria da Luz"></Teacher><Subject name="Lingua Portuguesa"></Subject>
    </Hour>
    <Hour name="1">
      <Teacher name="Giselle"></Teacher><Subject name="Biologia"></Subject>
    </Hour>
    <Hour name="2">
      <Teacher name="Silvania"></Teacher><Subject name="Matematica"></Subject>
    </Hour>
    <Hour name="3">
      <Teacher name="Lima"></Teacher><Subject name="Fisica"></Subject>
    </Hour>
    <Hour name="4">
      <Teacher name="Carlos"></Teacher><Subject name="Quimica"></Subject>
    </Hour>
   </Day>
   <Day name="Marti">
    <Hour name="0">
      <Teacher name="Terezinha"></Teacher><Subject name="Geografia"></Subject>
    </Hour>
    <Hour name="1">
      <Teacher name="Renata"></Teacher><Subject name="Educcacao Fisica"></Subject>
    </Hour>
    <Hour name="2">
      <Teacher name="Giselle"></Teacher><Subject name="Biologia"></Subject>
    </Hour>
    <Hour name="3">
      <Teacher name="Marli"></Teacher><Subject name="Historia"></Subject>
    </Hour>
    <Hour name="4">
      <Teacher name="Lima"></Teacher><Subject name="Fisica"></Subject>
    </Hour>
   </Day>
   <Day name="Miercuri">
    <Hour name="0">
      <Teacher name="Giselle"></Teacher><Subject name="Biologia"></Subject>
    </Hour>
    <Hour name="1">
      <Teacher name="Silvana"></Teacher><Subject name="Ingles"></Subject>
    </Hour>
    <Hour name="2">
      <Teacher name="Silvania"></Teacher><Subject name="Matematica"></Subject>
    </Hour>
    <Hour name="3">
      <Teacher name="Carlos"></Teacher><Subject name="Quimica"></Subject>
    </Hour>
    <Hour name="4">
      <Teacher name="Marli"></Teacher><Subject name="Historia"></Subject>
    </Hour>
   </Day>
   <Day name="Joi">
    <Hour name="0">
      <Teacher name="Lima"></Teacher><Subject name="Fisica"></Subject>
    </Hour>
    <Hour name="1">
      <Teacher name="Carlos"></Teacher><Subject name="Quimica"></Subject>
    </Hour>
    <Hour name="2">
      <Teacher name="Maria da Luz"></Teacher><Subject name="Lingua Portuguesa"></Subject>
    </Hour>
    <Hour name="3">
      <Teacher name="Gilmar"></Teacher><Subject name="Filosofia"></Subject>
    </Hour>
    <Hour name="4">
      <Teacher name="Terezinha"></Teacher><Subject name="Geografia"></Subject>
    </Hour>
   </Day>
   <Day name="Vineri">
    <Hour name="0">
      <Teacher name="Silvania"></Teacher><Subject name="Matematica"></Subject>
    </Hour>
    <Hour name="1">
      <Teacher name="Silvana"></Teacher><Subject name="Ingles"></Subject>
    </Hour>
    <Hour name="2">
      <Teacher name="Maria da Luz"></Teacher><Subject name="Lingua Portuguesa"></Subject>
    </Hour>
    <Hour name="3">
      <Teacher name="Renata"></Teacher><Subject name="Educcacao Fisica"></Subject>
    </Hour>
    <Hour name="4">
      <Teacher name="Gilmar"></Teacher><Subject name="Filosofia"></Subject>
    </Hour>
   </Day>
  </Subgroup>
  <Subgroup name="103 Grupo Automático Subgrupo Automático">
   <Day name="Luni">
    <Hour name="0">
      <Teacher name="Lima"></Teacher><Subject name="Fisica"></Subject>
    </Hour>
    <Hour name="1">
      <Teacher name="Bruna"></Teacher><Subject name="Matematica"></Subject>
    </Hour>
    <Hour name="2">
      <Teacher name="Giselle"></Teacher><Subject name="Biologia"></Subject>
    </Hour>
    <Hour name="3">
      <Teacher name="Marli"></Teacher><Subject name="Historia"></Subject>
    </Hour>
    <Hour name="4">
      <Teacher name="Maria da Luz"></Teacher><Subject name="Lingua Portuguesa"></Subject>
    </Hour>
   </Day>
   <Day name="Marti">
    <Hour name="0">
      <Teacher name="Marli"></Teacher><Subject name="Historia"></Subject>
    </Hour>
    <Hour name="1">
      <Teacher name="Terezinha"></Teacher><Subject name="Geografia"></Subject>
    </Hour>
    <Hour name="2">
      <Teacher name="Carlos"></Teacher><Subject name="Quimica"></Subject>
    </Hour>
    <Hour name="3">
      <Teacher name="Renata"></Teacher><Subject name="Educcacao Fisica"></Subject>
    </Hour>
    <Hour name="4">
      <Teacher name="Giselle"></Teacher><Subject name="Biologia"></Subject>
    </Hour>
   </Day>
   <Day name="Miercuri">
    <Hour name="0">
      <Teacher name="Silvana"></Teacher><Subject name="Ingles"></Subject>
    </Hour>
    <Hour name="1">
      <Teacher name="Giselle"></Teacher><Subject name="Biologia"></Subject>
    </Hour>
    <Hour name="2">
      <Teacher name="Renata"></Teacher><Subject name="Educcacao Fisica"></Subject>
    </Hour>
    <Hour name="3">
      <Teacher name="Bruna"></Teacher><Subject name="Matematica"></Subject>
    </Hour>
    <Hour name="4">
      <Teacher name="Carlos"></Teacher><Subject name="Quimica"></Subject>
    </Hour>
   </Day>
   <Day name="Joi">
    <Hour name="0">
      <Teacher name="Terezinha"></Teacher><Subject name="Geografia"></Subject>
    </Hour>
    <Hour name="1">
      <Teacher name="Lima"></Teacher><Subject name="Fisica"></Subject>
    </Hour>
    <Hour name="2">
      <Teacher name="Gilmar"></Teacher><Subject name="Filosofia"></Subject>
    </Hour>
    <Hour name="3">
      <Teacher name="Maria da Luz"></Teacher><Subject name="Lingua Portuguesa"></Subject>
    </Hour>
    <Hour name="4">
      <Teacher name="Carlos"></Teacher><Subject name="Quimica"></Subject>
    </Hour>
   </Day>
   <Day name="Vineri">
    <Hour name="0">
      <Teacher name="Lima"></Teacher><Subject name="Fisica"></Subject>
    </Hour>
    <Hour name="1">
      <Teacher name="Maria da Luz"></Teacher><Subject name="Lingua Portuguesa"></Subject>
    </Hour>
    <Hour name="2">
      <Teacher name="Gilmar"></Teacher><Subject name="Filosofia"></Subject>
    </Hour>
    <Hour name="3">
      <Teacher name="Silvana"></Teacher><Subject name="Ingles"></Subject>
    </Hour>
    <Hour name="4">
      <Teacher name="Bruna"></Teacher><Subject name="Matematica"></Subject>
    </Hour>
   </Day>
  </Subgroup>
  <Subgroup name="104 Grupo Automático Subgrupo Automático">
   <Day name="Luni">
    <Hour name="0">
      <Teacher name="Carlos"></Teacher><Subject name="Quimica"></Subject>
    </Hour>
    <Hour name="1">
      <Teacher name="Maria da Luz"></Teacher><Subject name="Lingua Portuguesa"></Subject>
    </Hour>
    <Hour name="2">
      <Teacher name="Viviane"></Teacher><Subject name="Geografia"></Subject>
    </Hour>
    <Hour name="3">
      <Teacher name="Giselle"></Teacher><Subject name="Biologia"></Subject>
    </Hour>
    <Hour name="4">
      <Teacher name="Lima"></Teacher><Subject name="Fisica"></Subject>
    </Hour>
   </Day>
   <Day name="Marti">
    <Hour name="0">
      <Teacher name="Carlos"></Teacher><Subject name="Quimica"></Subject>
    </Hour>
    <Hour name="1">
      <Teacher name="Bruna"></Teacher><Subject name="Matematica"></Subject>
    </Hour>
    <Hour name="2">
      <Teacher name="Lima"></Teacher><Subject name="Fisica"></Subject>
    </Hour>
    <Hour name="3">
      <Teacher name="Silvana"></Teacher><Subject name="Ingles"></Subject>
    </Hour>
    <Hour name="4">
      <Teacher name="Marli"></Teacher><Subject name="Historia"></Subject>
    </Hour>
   </Day>
   <Day name="Miercuri">
    <Hour name="0">
      <Teacher name="Bruna"></Teacher><Subject name="Matematica"></Subject>
    </Hour>
    <Hour name="1">
      <Teacher name="Renata"></Teacher><Subject name="Educcacao Fisica"></Subject>
    </Hour>
    <Hour name="2">
      <Teacher name="Giselle"></Teacher><Subject name="Biologia"></Subject>
    </Hour>
    <Hour name="3">
      <Teacher name="Marli"></Teacher><Subject name="Historia"></Subject>
    </Hour>
    <Hour name="4">
      <Teacher name="Silvana"></Teacher><Subject name="Ingles"></Subject>
    </Hour>
   </Day>
   <Day name="Joi">
    <Hour name="0">
      <Teacher name="Carlos"></Teacher><Subject name="Quimica"></Subject>
    </Hour>
    <Hour name="1">
      <Teacher name="Gilmar"></Teacher><Subject name="Filosofia"></Subject>
    </Hour>
    <Hour name="2">
      <Teacher name="Giselle"></Teacher><Subject name="Biologia"></Subject>
    </Hour>
    <Hour name="3">
      <Teacher name="Bruna"></Teacher><Subject name="Matematica"></Subject>
    </Hour>
    <Hour name="4">
      <Teacher name="Maria da Luz"></Teacher><Subject name="Lingua Portuguesa"></Subject>
    </Hour>
   </Day>
   <Day name="Vineri">
    <Hour name="0">
      <Teacher name="Renata"></Teacher><Subject name="Educcacao Fisica"></Subject>
    </Hour>
    <Hour name="1">
      <Teacher name="Gilmar"></Teacher><Subject name="Filosofia"></Subject>
    </Hour>
    <Hour name="2">
      <Teacher name="Lima"></Teacher><Subject name="Fisica"></Subject>
    </Hour>
    <Hour name="3">
      <Teacher name="Viviane"></Teacher><Subject name="Geografia"></Subject>
    </Hour>
    <Hour name="4">
      <Teacher name="Maria da Luz"></Teacher><Subject name="Lingua Portuguesa"></Subject>
    </Hour>
   </Day>
  </Subgroup>
  <Subgroup name="111 Grupo Automático Subgrupo Automático">
   <Day name="Luni">
    <Hour name="0">
      <Teacher name="Viviane"></Teacher><Subject name="Geografia"></Subject>
    </Hour>
    <Hour name="1">
      <Teacher name="Carlos"></Teacher><Subject name="Quimica"></Subject>
    </Hour>
    <Hour name="2">
      <Teacher name="Maria da Luz"></Teacher><Subject name="Lingua Portuguesa"></Subject>
    </Hour>
    <Hour name="3">
      <Teacher name="Andreia"></Teacher><Subject name="Historia"></Subject>
    </Hour>
    <Hour name="4">
      <Teacher name="Andreia"></Teacher><Subject name="Historia"></Subject>
    </Hour>
   </Day>
   <Day name="Marti">
    <Hour name="0">
      <Teacher name="Andreia2"></Teacher><Subject name="Fisica"></Subject>
    </Hour>
    <Hour name="1">
      <Teacher name="Carlos"></Teacher><Subject name="Quimica"></Subject>
    </Hour>
    <Hour name="2">
      <Teacher name="Silvana"></Teacher><Subject name="Ingles"></Subject>
    </Hour>
    <Hour name="3">
      <Teacher name="Wellington"></Teacher><Subject name="Matematica"></Subject>
    </Hour>
    <Hour name="4">
      <Teacher name="Renata"></Teacher><Subject name="Educcacao Fisica"></Subject>
    </Hour>
   </Day>
   <Day name="Miercuri">
    <Hour name="0">
      <Teacher name="Carlos"></Teacher><Subject name="Quimica"></Subject>
    </Hour>
    <Hour name="1">
      <Teacher name="Helvecio"></Teacher><Subject name="Filosofia"></Subject>
    </Hour>
    <Hour name="2">
      <Teacher name="Osvaldo"></Teacher><Subject name="Biologia"></Subject>
    </Hour>
    <Hour name="3">
      <Teacher name="Osvaldo"></Teacher><Subject name="Biologia"></Subject>
    </Hour>
    <Hour name="4">
      <Teacher name="Andreia2"></Teacher><Subject name="Fisica"></Subject>
    </Hour>
   </Day>
   <Day name="Joi">
    <Hour name="0">
      <Teacher name="Wellington"></Teacher><Subject name="Matematica"></Subject>
    </Hour>
    <Hour name="1">
      <Teacher name="Maria da Luz"></Teacher><Subject name="Lingua Portuguesa"></Subject>
    </Hour>
    <Hour name="2">
      <Teacher name="Helvecio"></Teacher><Subject name="Filosofia"></Subject>
    </Hour>
    <Hour name="3">
      <Teacher name="Viviane"></Teacher><Subject name="Geografia"></Subject>
    </Hour>
    <Hour name="4">
      <Teacher name="Andreia2"></Teacher><Subject name="Fisica"></Subject>
    </Hour>
   </Day>
   <Day name="Vineri">
    <Hour name="0">
      <Teacher name="Silvana"></Teacher><Subject name="Ingles"></Subject>
    </Hour>
    <Hour name="1">
      <Teacher name="Wellington"></Teacher><Subject name="Matematica"></Subject>
    </Hour>
    <Hour name="2">
      <Teacher name="Osvaldo"></Teacher><Subject name="Biologia"></Subject>
    </Hour>
    <Hour name="3">
      <Teacher name="Maria da Luz"></Teacher><Subject name="Lingua Portuguesa"></Subject>
    </Hour>
    <Hour name="4">
      <Teacher name="Renata"></Teacher><Subject name="Educcacao Fisica"></Subject>
    </Hour>
   </Day>
  </Subgroup>
  <Subgroup name="201 Grupo Automático Subgrupo Automático">
   <Day name="Luni">
    <Hour name="0">
      <Teacher name="Silvania"></Teacher><Subject name="Matematica"></Subject>
    </Hour>
    <Hour name="1">
      <Teacher name="Tania"></Teacher><Subject name="Lingua Portuguesa"></Subject>
    </Hour>
    <Hour name="2">
      <Teacher name="Lima"></Teacher><Subject name="Fisica"></Subject>
    </Hour>
    <Hour name="3">
      <Teacher name="Carlos"></Teacher><Subject name="Quimica"></Subject>
    </Hour>
    <Hour name="4">
      <Teacher name="Cristiane"></Teacher><Subject name="Biologia"></Subject>
    </Hour>
   </Day>
   <Day name="Marti">
    <Hour name="0">
      <Teacher name="Cristiane"></Teacher><Subject name="Biologia"></Subject>
    </Hour>
    <Hour name="1">
      <Teacher name="Aparacida"></Teacher><Subject name="Geografia"></Subject>
    </Hour>
    <Hour name="2">
      <Teacher name="Rosilene"></Teacher><Subject name="Ingles"></Subject>
    </Hour>
    <Hour name="3">
      <Teacher name="Silvania"></Teacher><Subject name="Matematica"></Subject>
    </Hour>
    <Hour name="4">
      <Teacher name="Dulcimar"></Teacher><Subject name="Historia"></Subject>
    </Hour>
   </Day>
   <Day name="Miercuri">
    <Hour name="0">
      <Teacher name="Renata"></Teacher><Subject name="Educcacao Fisica"></Subject>
    </Hour>
    <Hour name="1">
      <Teacher name="Silvania"></Teacher><Subject name="Matematica"></Subject>
    </Hour>
    <Hour name="2">
      <Teacher name="Cristiane"></Teacher><Subject name="Biologia"></Subject>
    </Hour>
    <Hour name="3">
      <Teacher name="Rosilene"></Teacher><Subject name="Ingles"></Subject>
    </Hour>
    <Hour name="4">
      <Teacher name="Dulcimar"></Teacher><Subject name="Historia"></Subject>
    </Hour>
   </Day>
   <Day name="Joi">
    <Hour name="0">
      <Teacher name="Dulcimar"></Teacher><Subject name="Historia"></Subject>
    </Hour>
    <Hour name="1">
      <Teacher name="Helvecio"></Teacher><Subject name="Filosofia"></Subject>
    </Hour>
    <Hour name="2">
      <Teacher name="Tania"></Teacher><Subject name="Lingua Portuguesa"></Subject>
    </Hour>
    <Hour name="3">
      <Teacher name="Carlos"></Teacher><Subject name="Quimica"></Subject>
    </Hour>
    <Hour name="4">
      <Teacher name="Lima"></Teacher><Subject name="Fisica"></Subject>
    </Hour>
   </Day>
   <Day name="Vineri">
    <Hour name="0">
      <Teacher name="Aparacida"></Teacher><Subject name="Geografia"></Subject>
    </Hour>
    <Hour name="1">
      <Teacher name="Silvania"></Teacher><Subject name="Matematica"></Subject>
    </Hour>
    <Hour name="2">
      <Teacher name="Renata"></Teacher><Subject name="Educcacao Fisica"></Subject>
    </Hour>
    <Hour name="3">
      <Teacher name="Helvecio"></Teacher><Subject name="Filosofia"></Subject>
    </Hour>
    <Hour name="4">
      <Teacher name="Tania"></Teacher><Subject name="Lingua Portuguesa"></Subject>
    </Hour>
   </Day>
  </Subgroup>
  <Subgroup name="202 Grupo Automático Subgrupo Automático">
   <Day name="Luni">
    <Hour name="0">
      <Teacher name="Tania"></Teacher><Subject name="Lingua Portuguesa"></Subject>
    </Hour>
    <Hour name="1">
      <Teacher name="Aparacida"></Teacher><Subject name="Geografia"></Subject>
    </Hour>
    <Hour name="2">
      <Teacher name="Cristiane"></Teacher><Subject name="Biologia"></Subject>
    </Hour>
    <Hour name="3">
      <Teacher name="Silvania"></Teacher><Subject name="Matematica"></Subject>
    </Hour>
    <Hour name="4">
      <Teacher name="Rosilene"></Teacher><Subject name="Ingles"></Subject>
    </Hour>
   </Day>
   <Day name="Marti">
    <Hour name="0">
      <Teacher name="Renata"></Teacher><Subject name="Educcacao Fisica"></Subject>
    </Hour>
    <Hour name="1">
      <Teacher name="Lima"></Teacher><Subject name="Fisica"></Subject>
    </Hour>
    <Hour name="2">
      <Teacher name="Dulcimar"></Teacher><Subject name="Historia"></Subject>
    </Hour>
    <Hour name="3">
      <Teacher name="Carlos"></Teacher><Subject name="Quimica"></Subject>
    </Hour>
    <Hour name="4">
      <Teacher name="Silvania"></Teacher><Subject name="Matematica"></Subject>
    </Hour>
   </Day>
   <Day name="Miercuri">
    <Hour name="0">
      <Teacher name="Cristiane"></Teacher><Subject name="Biologia"></Subject>
    </Hour>
    <Hour name="1">
      <Teacher name="Aparacida"></Teacher><Subject name="Geografia"></Subject>
    </Hour>
    <Hour name="2">
      <Teacher name="Carlos"></Teacher><Subject name="Quimica"></Subject>
    </Hour>
    <Hour name="3">
      <Teacher name="Renata"></Teacher><Subject name="Educcacao Fisica"></Subject>
    </Hour>
    <Hour name="4">
      <Teacher name="Silvania"></Teacher><Subject name="Matematica"></Subject>
    </Hour>
   </Day>
   <Day name="Joi">
    <Hour name="0">
      <Teacher name="Helvecio"></Teacher><Subject name="Filosofia"></Subject>
    </Hour>
    <Hour name="1">
      <Teacher name="Tania"></Teacher><Subject name="Lingua Portuguesa"></Subject>
    </Hour>
    <Hour name="2">
      <Teacher name="Rosilene"></Teacher><Subject name="Ingles"></Subject>
    </Hour>
    <Hour name="3">
      <Teacher name="Lima"></Teacher><Subject name="Fisica"></Subject>
    </Hour>
    <Hour name="4">
      <Teacher name="Dulcimar"></Teacher><Subject name="Historia"></Subject>
    </Hour>
   </Day>
   <Day name="Vineri">
    <Hour name="0">
      <Teacher name="Helvecio"></Teacher><Subject name="Filosofia"></Subject>
    </Hour>
    <Hour name="1">
      <Teacher name="Cristiane"></Teacher><Subject name="Biologia"></Subject>
    </Hour>
    <Hour name="2">
      <Teacher name="Silvania"></Teacher><Subject name="Matematica"></Subject>
    </Hour>
    <Hour name="3">
      <Teacher name="Tania"></Teacher><Subject name="Lingua Portuguesa"></Subject>
    </Hour>
    <Hour name="4">
      <Teacher name="Dulcimar"></Teacher><Subject name="Historia"></Subject>
    </Hour>
   </Day>
  </Subgroup>
  <Subgroup name="203 Grupo Automático Subgrupo Automático">
   <Day name="Luni">
    <Hour name="0">
      <Teacher name="Cristiane"></Teacher><Subject name="Biologia"></Subject>
    </Hour>
    <Hour name="1">
      <Teacher name="Silvania"></Teacher><Subject name="Matematica"></Subject>
    </Hour>
    <Hour name="2">
      <Teacher name="Rosilene"></Teacher><Subject name="Ingles"></Subject>
    </Hour>
    <Hour name="3">
      <Teacher name="Tania"></Teacher><Subject name="Lingua Portuguesa"></Subject>
    </Hour>
    <Hour name="4">
      <Teacher name="Marcelo"></Teacher><Subject name="Quimica"></Subject>
    </Hour>
   </Day>
   <Day name="Marti">
    <Hour name="0">
      <Teacher name="Silvania"></Teacher><Subject name="Matematica"></Subject>
    </Hour>
    <Hour name="1">
      <Teacher name="Tania"></Teacher><Subject name="Lingua Portuguesa"></Subject>
    </Hour>
    <Hour name="2">
      <Teacher name="Aparacida"></Teacher><Subject name="Geografia"></Subject>
    </Hour>
    <Hour name="3">
      <Teacher name="Lima"></Teacher><Subject name="Fisica"></Subject>
    </Hour>
    <Hour name="4">
      <Teacher name="Cristiane"></Teacher><Subject name="Biologia"></Subject>
    </Hour>
   </Day>
   <Day name="Miercuri">
    <Hour name="0">
      <Teacher name="Dulcimar"></Teacher><Subject name="Historia"></Subject>
    </Hour>
    <Hour name="1">
      <Teacher name="Anderson"></Teacher><Subject name="Educcacao Fisica"></Subject>
    </Hour>
    <Hour name="2">
      <Teacher name="Helvecio"></Teacher><Subject name="Filosofia"></Subject>
    </Hour>
    <Hour name="3">
      <Teacher name="Silvania"></Teacher><Subject name="Matematica"></Subject>
    </Hour>
    <Hour name="4">
      <Teacher name="Rosilene"></Teacher><Subject name="Ingles"></Subject>
    </Hour>
   </Day>
   <Day name="Joi">
    <Hour name="0">
      <Teacher name="Aparacida"></Teacher><Subject name="Geografia"></Subject>
    </Hour>
    <Hour name="1">
      <Teacher name="Marcelo"></Teacher><Subject name="Quimica"></Subject>
    </Hour>
    <Hour name="2">
      <Teacher name="Lima"></Teacher><Subject name="Fisica"></Subject>
    </Hour>
    <Hour name="3">
      <Teacher name="Dulcimar"></Teacher><Subject name="Historia"></Subject>
    </Hour>
    <Hour name="4">
      <Teacher name="Helvecio"></Teacher><Subject name="Filosofia"></Subject>
    </Hour>
   </Day>
   <Day name="Vineri">
    <Hour name="0">
      <Teacher name="Anderson"></Teacher><Subject name="Educcacao Fisica"></Subject>
    </Hour>
    <Hour name="1">
      <Teacher name="Dulcimar"></Teacher><Subject name="Historia"></Subject>
    </Hour>
    <Hour name="2">
      <Teacher name="Tania"></Teacher><Subject name="Lingua Portuguesa"></Subject>
    </Hour>
    <Hour name="3">
      <Teacher name="Cristiane"></Teacher><Subject name="Biologia"></Subject>
    </Hour>
    <Hour name="4">
      <Teacher name="Silvania"></Teacher><Subject name="Matematica"></Subject>
    </Hour>
   </Day>
  </Subgroup>
  <Subgroup name="204 Grupo Automático Subgrupo Automático">
   <Day name="Luni">
    <Hour name="0">
      <Teacher name="Rosilene"></Teacher><Subject name="Ingles"></Subject>
    </Hour>
    <Hour name="1">
      <Teacher name="Anderson"></Teacher><Subject name="Educcacao Fisica"></Subject>
    </Hour>
    <Hour name="2">
      <Teacher name="Marcelo"></Teacher><Subject name="Quimica"></Subject>
    </Hour>
    <Hour name="3">
      <Teacher name="Bruna"></Teacher><Subject name="Matematica"></Subject>
    </Hour>
    <Hour name="4">
      <Teacher name="Tania"></Teacher><Subject name="Lingua Portuguesa"></Subject>
    </Hour>
   </Day>
   <Day name="Marti">
    <Hour name="0">
      <Teacher name="Marcelo"></Teacher><Subject name="Quimica"></Subject>
    </Hour>
    <Hour name="1">
      <Teacher name="Cristiane"></Teacher><Subject name="Biologia"></Subject>
    </Hour>
    <Hour name="2">
      <Teacher name="Andreia2"></Teacher><Subject name="Fisica"></Subject>
    </Hour>
    <Hour name="3">
      <Teacher name="Anderson"></Teacher><Subject name="Educcacao Fisica"></Subject>
    </Hour>
    <Hour name="4">
      <Teacher name="Tania"></Teacher><Subject name="Lingua Portuguesa"></Subject>
    </Hour>
   </Day>
   <Day name="Miercuri">
    <Hour name="0">
      <Teacher name="Rosilene"></Teacher><Subject name="Ingles"></Subject>
    </Hour>
    <Hour name="1">
      <Teacher name="Dulcimar"></Teacher><Subject name="Historia"></Subject>
    </Hour>
    <Hour name="2">
      <Teacher name="Bruna"></Teacher><Subject name="Matematica"></Subject>
    </Hour>
    <Hour name="3">
      <Teacher name="Cristiane"></Teacher><Subject name="Biologia"></Subject>
    </Hour>
    <Hour name="4">
      <Teacher name="Helvecio"></Teacher><Subject name="Filosofia"></Subject>
    </Hour>
   </Day>
   <Day name="Joi">
    <Hour name="0">
      <Teacher name="Viviane"></Teacher><Subject name="Geografia"></Subject>
    </Hour>
    <Hour name="1">
      <Teacher name="Andreia2"></Teacher><Subject name="Fisica"></Subject>
    </Hour>
    <Hour name="2">
      <Teacher name="Dulcimar"></Teacher><Subject name="Historia"></Subject>
    </Hour>
    <Hour name="3">
      <Teacher name="Tania"></Teacher><Subject name="Lingua Portuguesa"></Subject>
    </Hour>
    <Hour name="4">
      <Teacher name="Bruna"></Teacher><Subject name="Matematica"></Subject>
    </Hour>
   </Day>
   <Day name="Vineri">
    <Hour name="0">
      <Teacher name="Dulcimar"></Teacher><Subject name="Historia"></Subject>
    </Hour>
    <Hour name="1">
      <Teacher name="Helvecio"></Teacher><Subject name="Filosofia"></Subject>
    </Hour>
    <Hour name="2">
      <Teacher name="Viviane"></Teacher><Subject name="Geografia"></Subject>
    </Hour>
    <Hour name="3">
      <Teacher name="Bruna"></Teacher><Subject name="Matematica"></Subject>
    </Hour>
    <Hour name="4">
      <Teacher name="Cristiane"></Teacher><Subject name="Biologia"></Subject>
    </Hour>
   </Day>
  </Subgroup>
  <Subgroup name="205 Grupo Automático Subgrupo Automático">
   <Day name="Luni">
    <Hour name="0">
      <Teacher name="Bruna"></Teacher><Subject name="Matematica"></Subject>
    </Hour>
    <Hour name="1">
      <Teacher name="Cristiane"></Teacher><Subject name="Biologia"></Subject>
    </Hour>
    <Hour name="2">
      <Teacher name="Tania"></Teacher><Subject name="Lingua Portuguesa"></Subject>
    </Hour>
    <Hour name="3">
      <Teacher name="Rosilene"></Teacher><Subject name="Ingles"></Subject>
    </Hour>
    <Hour name="4">
      <Teacher name="Viviane"></Teacher><Subject name="Geografia"></Subject>
    </Hour>
   </Day>
   <Day name="Marti">
    <Hour name="0">
      <Teacher name="Dulcimar"></Teacher><Subject name="Historia"></Subject>
    </Hour>
    <Hour name="1">
      <Teacher name="Rosilene"></Teacher><Subject name="Ingles"></Subject>
    </Hour>
    <Hour name="2">
      <Teacher name="Anderson"></Teacher><Subject name="Educcacao Fisica"></Subject>
    </Hour>
    <Hour name="3">
      <Teacher name="Tania"></Teacher><Subject name="Lingua Portuguesa"></Subject>
    </Hour>
    <Hour name="4">
      <Teacher name="Marcelo"></Teacher><Subject name="Quimica"></Subject>
    </Hour>
   </Day>
   <Day name="Miercuri">
    <Hour name="0">
      <Teacher name="Marcelo"></Teacher><Subject name="Quimica"></Subject>
    </Hour>
    <Hour name="1">
      <Teacher name="Cristiane"></Teacher><Subject name="Biologia"></Subject>
    </Hour>
    <Hour name="2">
      <Teacher name="Anderson"></Teacher><Subject name="Educcacao Fisica"></Subject>
    </Hour>
    <Hour name="3">
      <Teacher name="Helvecio"></Teacher><Subject name="Filosofia"></Subject>
    </Hour>
    <Hour name="4">
      <Teacher name="Bruna"></Teacher><Subject name="Matematica"></Subject>
    </Hour>
   </Day>
   <Day name="Joi">
    <Hour name="0">
      <Teacher name="Bruna"></Teacher><Subject name="Matematica"></Subject>
    </Hour>
    <Hour name="1">
      <Teacher name="Dulcimar"></Teacher><Subject name="Historia"></Subject>
    </Hour>
    <Hour name="2">
      <Teacher name="Andreia2"></Teacher><Subject name="Fisica"></Subject>
    </Hour>
    <Hour name="3">
      <Teacher name="Helvecio"></Teacher><Subject name="Filosofia"></Subject>
    </Hour>
    <Hour name="4">
      <Teacher name="Tania"></Teacher><Subject name="Lingua Portuguesa"></Subject>
    </Hour>
   </Day>
   <Day name="Vineri">
    <Hour name="0">
      <Teacher name="Cristiane"></Teacher><Subject name="Biologia"></Subject>
    </Hour>
    <Hour name="1">
      <Teacher name="Bruna"></Teacher><Subject name="Matematica"></Subject>
    </Hour>
    <Hour name="2">
      <Teacher name="Andreia2"></Teacher><Subject name="Fisica"></Subject>
    </Hour>
    <Hour name="3">
      <Teacher name="Dulcimar"></Teacher><Subject name="Historia"></Subject>
    </Hour>
    <Hour name="4">
      <Teacher name="Viviane"></Teacher><Subject name="Geografia"></Subject>
    </Hour>
   </Day>
  </Subgroup>
  <Subgroup name="206 Grupo Automático Subgrupo Automático">
   <Day name="Luni">
    <Hour name="0">
      <Teacher name="Marcelo"></Teacher><Subject name="Quimica"></Subject>
    </Hour>
    <Hour name="1">
      <Teacher name="Viviane"></Teacher><Subject name="Geografia"></Subject>
    </Hour>
    <Hour name="2">
      <Teacher name="Anderson"></Teacher><Subject name="Educcacao Fisica"></Subject>
    </Hour>
    <Hour name="3">
      <Teacher name="Cristiane"></Teacher><Subject name="Biologia"></Subject>
    </Hour>
    <Hour name="4">
      <Teacher name="Bruna"></Teacher><Subject name="Matematica"></Subject>
    </Hour>
   </Day>
   <Day name="Marti">
    <Hour name="0">
      <Teacher name="Tania"></Teacher><Subject name="Lingua Portuguesa"></Subject>
    </Hour>
    <Hour name="1">
      <Teacher name="Andreia2"></Teacher><Subject name="Fisica"></Subject>
    </Hour>
    <Hour name="2">
      <Teacher name="Cristiane"></Teacher><Subject name="Biologia"></Subject>
    </Hour>
    <Hour name="3">
      <Teacher name="Dulcimar"></Teacher><Subject name="Historia"></Subject>
    </Hour>
    <Hour name="4">
      <Teacher name="Rosilene"></Teacher><Subject name="Ingles"></Subject>
    </Hour>
   </Day>
   <Day name="Miercuri">
    <Hour name="0">
      <Teacher name="Helvecio"></Teacher><Subject name="Filosofia"></Subject>
    </Hour>
    <Hour name="1">
      <Teacher name="Bruna"></Teacher><Subject name="Matematica"></Subject>
    </Hour>
    <Hour name="2">
      <Teacher name="Dulcimar"></Teacher><Subject name="Historia"></Subject>
    </Hour>
    <Hour name="3">
      <Teacher name="Anderson"></Teacher><Subject name="Educcacao Fisica"></Subject>
    </Hour>
    <Hour name="4">
      <Teacher name="Cristiane"></Teacher><Subject name="Biologia"></Subject>
    </Hour>
   </Day>
   <Day name="Joi">
    <Hour name="0">
      <Teacher name="Tania"></Teacher><Subject name="Lingua Portuguesa"></Subject>
    </Hour>
    <Hour name="1">
      <Teacher name="Viviane"></Teacher><Subject name="Geografia"></Subject>
    </Hour>
    <Hour name="2">
      <Teacher name="Bruna"></Teacher><Subject name="Matematica"></Subject>
    </Hour>
    <Hour name="3">
      <Teacher name="Rosilene"></Teacher><Subject name="Ingles"></Subject>
    </Hour>
    <Hour name="4">
      <Teacher name="Marcelo"></Teacher><Subject name="Quimica"></Subject>
    </Hour>
   </Day>
   <Day name="Vineri">
    <Hour name="0">
      <Teacher name="Bruna"></Teacher><Subject name="Matematica"></Subject>
    </Hour>
    <Hour name="1">
      <Teacher name="Tania"></Teacher><Subject name="Lingua Portuguesa"></Subject>
    </Hour>
    <Hour name="2">
      <Teacher name="Dulcimar"></Teacher><Subject name="Historia"></Subject>
    </Hour>
    <Hour name="3">
      <Teacher name="Andreia2"></Teacher><Subject name="Fisica"></Subject>
    </Hour>
    <Hour name="4">
      <Teacher name="Helvecio"></Teacher><Subject name="Filosofia"></Subject>
    </Hour>
   </Day>
  </Subgroup>
  <Subgroup name="301 Grupo Automático Subgrupo Automático">
   <Day name="Luni">
    <Hour name="0">
      <Teacher name="Luzia"></Teacher><Subject name="Lingua Portuguesa"></Subject>
    </Hour>
    <Hour name="1">
      <Teacher name="Marli"></Teacher><Subject name="Historia"></Subject>
    </Hour>
    <Hour name="2">
      <Teacher name="Wellington"></Teacher><Subject name="Matematica"></Subject>
    </Hour>
    <Hour name="3">
      <Teacher name="Marcelo"></Teacher><Subject name="Quimica"></Subject>
    </Hour>
    <Hour name="4">
      <Teacher name="Giselle"></Teacher><Subject name="Biologia"></Subject>
    </Hour>
   </Day>
   <Day name="Marti">
    <Hour name="0">
      <Teacher name="Aparacida"></Teacher><Subject name="Geografia"></Subject>
    </Hour>
    <Hour name="1">
      <Teacher name="Roberto"></Teacher><Subject name="Sociologia"></Subject>
    </Hour>
    <Hour name="2">
      <Teacher name="Wellington"></Teacher><Subject name="Matematica"></Subject>
    </Hour>
    <Hour name="3">
      <Teacher name="Luzia"></Teacher><Subject name="Lingua Portuguesa"></Subject>
    </Hour>
    <Hour name="4">
      <Teacher name="Carla"></Teacher><Subject name="Artes"></Subject>
    </Hour>
   </Day>
   <Day name="Miercuri">
    <Hour name="0">
      <Teacher name="Luzia"></Teacher><Subject name="Lingua Portuguesa"></Subject>
    </Hour>
    <Hour name="1">
      <Teacher name="Rosilene"></Teacher><Subject name="Ingles"></Subject>
    </Hour>
    <Hour name="2">
      <Teacher name="Marcelo"></Teacher><Subject name="Quimica"></Subject>
    </Hour>
    <Hour name="3">
      <Teacher name="Andreia2"></Teacher><Subject name="Fisica"></Subject>
    </Hour>
    <Hour name="4">
      <Teacher name="Anderson"></Teacher><Subject name="Educcacao Fisica"></Subject>
    </Hour>
   </Day>
   <Day name="Joi">
    <Hour name="0">
      <Teacher name="Giselle"></Teacher><Subject name="Biologia"></Subject>
    </Hour>
    <Hour name="1">
      <Teacher name="Aparacida"></Teacher><Subject name="Geografia"></Subject>
    </Hour>
    <Hour name="2">
      <Teacher name="Marli"></Teacher><Subject name="Historia"></Subject>
    </Hour>
    <Hour name="3">
      <Teacher name="Andreia2"></Teacher><Subject name="Fisica"></Subject>
    </Hour>
    <Hour name="4">
      <Teacher name="Rosilene"></Teacher><Subject name="Ingles"></Subject>
    </Hour>
   </Day>
   <Day name="Vineri">
    <Hour name="0">
      <Teacher name="Luzia"></Teacher><Subject name="Lingua Portuguesa"></Subject>
    </Hour>
    <Hour name="1">
      <Teacher name="Aparacida"></Teacher><Subject name="Geografia"></Subject>
    </Hour>
    <Hour name="2">
      <Teacher name="Wellington"></Teacher><Subject name="Matematica"></Subject>
    </Hour>
    <Hour name="3">
      <Teacher name="Roberto"></Teacher><Subject name="Sociologia"></Subject>
    </Hour>
    <Hour name="4">
      <Teacher name="Anderson"></Teacher><Subject name="Educcacao Fisica"></Subject>
    </Hour>
   </Day>
  </Subgroup>
  <Subgroup name="302 Grupo Automático Subgrupo Automático">
   <Day name="Luni">
    <Hour name="0">
      <Teacher name="Giselle"></Teacher><Subject name="Biologia"></Subject>
    </Hour>
    <Hour name="1">
      <Teacher name="Rosilene"></Teacher><Subject name="Ingles"></Subject>
    </Hour>
    <Hour name="2">
      <Teacher name="Roberto"></Teacher><Subject name="Sociologia"></Subject>
    </Hour>
    <Hour name="3">
      <Teacher name="Aparacida"></Teacher><Subject name="Geografia"></Subject>
    </Hour>
    <Hour name="4">
      <Teacher name="Luzia"></Teacher><Subject name="Lingua Portuguesa"></Subject>
    </Hour>
   </Day>
   <Day name="Marti">
    <Hour name="0">
      <Teacher name="Carla"></Teacher><Subject name="Artes"></Subject>
    </Hour>
    <Hour name="1">
      <Teacher name="Luzia"></Teacher><Subject name="Lingua Portuguesa"></Subject>
    </Hour>
    <Hour name="2">
      <Teacher name="Marcelo"></Teacher><Subject name="Quimica"></Subject>
    </Hour>
    <Hour name="3">
      <Teacher name="Andreia2"></Teacher><Subject name="Fisica"></Subject>
    </Hour>
    <Hour name="4">
      <Teacher name="Wellington"></Teacher><Subject name="Matematica"></Subject>
    </Hour>
   </Day>
   <Day name="Miercuri">
    <Hour name="0">
      <Teacher name="Anderson"></Teacher><Subject name="Educcacao Fisica"></Subject>
    </Hour>
    <Hour name="1">
      <Teacher name="Marli"></Teacher><Subject name="Historia"></Subject>
    </Hour>
    <Hour name="2">
      <Teacher name="Aparacida"></Teacher><Subject name="Geografia"></Subject>
    </Hour>
    <Hour name="3">
      <Teacher name="Marcelo"></Teacher><Subject name="Quimica"></Subject>
    </Hour>
    <Hour name="4">
      <Teacher name="Luzia"></Teacher><Subject name="Lingua Portuguesa"></Subject>
    </Hour>
   </Day>
   <Day name="Joi">
    <Hour name="0">
      <Teacher name="Rosilene"></Teacher><Subject name="Ingles"></Subject>
    </Hour>
    <Hour name="1">
      <Teacher name="Marli"></Teacher><Subject name="Historia"></Subject>
    </Hour>
    <Hour name="2">
      <Teacher name="Roberto"></Teacher><Subject name="Sociologia"></Subject>
    </Hour>
    <Hour name="3">
      <Teacher name="Giselle"></Teacher><Subject name="Biologia"></Subject>
    </Hour>
    <Hour name="4">
      <Teacher name="Wellington"></Teacher><Subject name="Matematica"></Subject>
    </Hour>
   </Day>
   <Day name="Vineri">
    <Hour name="0">
      <Teacher name="Andreia2"></Teacher><Subject name="Fisica"></Subject>
    </Hour>
    <Hour name="1">
      <Teacher name="Luzia"></Teacher><Subject name="Lingua Portuguesa"></Subject>
    </Hour>
    <Hour name="2">
      <Teacher name="Anderson"></Teacher><Subject name="Educcacao Fisica"></Subject>
    </Hour>
    <Hour name="3">
      <Teacher name="Aparacida"></Teacher><Subject name="Geografia"></Subject>
    </Hour>
    <Hour name="4">
      <Teacher name="Wellington"></Teacher><Subject name="Matematica"></Subject>
    </Hour>
   </Day>
  </Subgroup>
  <Subgroup name="303 Grupo Automático Subgrupo Automático">
   <Day name="Luni">
    <Hour name="0">
      <Teacher name="Aparacida"></Teacher><Subject name="Geografia"></Subject>
    </Hour>
    <Hour name="1">
      <Teacher name="Roberto"></Teacher><Subject name="Sociologia"></Subject>
    </Hour>
    <Hour name="2">
      <Teacher name="Luzia"></Teacher><Subject name="Lingua Portuguesa"></Subject>
    </Hour>
    <Hour name="3">
      <Teacher name="Anderson"></Teacher><Subject name="Educcacao Fisica"></Subject>
    </Hour>
    <Hour name="4">
      <Teacher name="Marli"></Teacher><Subject name="Historia"></Subject>
    </Hour>
   </Day>
   <Day name="Marti">
    <Hour name="0">
      <Teacher name="Wellington"></Teacher><Subject name="Matematica"></Subject>
    </Hour>
    <Hour name="1">
      <Teacher name="Carla"></Teacher><Subject name="Artes"></Subject>
    </Hour>
    <Hour name="2">
      <Teacher name="Roberto"></Teacher><Subject name="Sociologia"></Subject>
    </Hour>
    <Hour name="3">
      <Teacher name="Rosilene"></Teacher><Subject name="Ingles"></Subject>
    </Hour>
    <Hour name="4">
      <Teacher name="Luzia"></Teacher><Subject name="Lingua Portuguesa"></Subject>
    </Hour>
   </Day>
   <Day name="Miercuri">
    <Hour name="0">
      <Teacher name="Marli"></Teacher><Subject name="Historia"></Subject>
    </Hour>
    <Hour name="1">
      <Teacher name="Marcelo"></Teacher><Subject name="Quimica"></Subject>
    </Hour>
    <Hour name="2">
      <Teacher name="Andreia2"></Teacher><Subject name="Fisica"></Subject>
    </Hour>
    <Hour name="3">
      <Teacher name="Luzia"></Teacher><Subject name="Lingua Portuguesa"></Subject>
    </Hour>
    <Hour name="4">
      <Teacher name="Giselle"></Teacher><Subject name="Biologia"></Subject>
    </Hour>
   </Day>
   <Day name="Joi">
    <Hour name="0">
      <Teacher name="Marcelo"></Teacher><Subject name="Quimica"></Subject>
    </Hour>
    <Hour name="1">
      <Teacher name="Rosilene"></Teacher><Subject name="Ingles"></Subject>
    </Hour>
    <Hour name="2">
      <Teacher name="Aparacida"></Teacher><Subject name="Geografia"></Subject>
    </Hour>
    <Hour name="3">
      <Teacher name="Wellington"></Teacher><Subject name="Matematica"></Subject>
    </Hour>
    <Hour name="4">
      <Teacher name="Giselle"></Teacher><Subject name="Biologia"></Subject>
    </Hour>
   </Day>
   <Day name="Vineri">
    <Hour name="0">
      <Teacher name="Wellington"></Teacher><Subject name="Matematica"></Subject>
    </Hour>
    <Hour name="1">
      <Teacher name="Andreia2"></Teacher><Subject name="Fisica"></Subject>
    </Hour>
    <Hour name="2">
      <Teacher name="Aparacida"></Teacher><Subject name="Geografia"></Subject>
    </Hour>
    <Hour name="3">
      <Teacher name="Anderson"></Teacher><Subject name="Educcacao Fisica"></Subject>
    </Hour>
    <Hour name="4">
      <Teacher name="Luzia"></Teacher><Subject name="Lingua Portuguesa"></Subject>
    </Hour>
   </Day>
  </Subgroup>
  <Subgroup name="304 Grupo Automático Subgrupo Automático">
   <Day name="Luni">
    <Hour name="0">
      <Teacher name="Anderson"></Teacher><Subject name="Educcacao Fisica"></Subject>
    </Hour>
    <Hour name="1">
      <Teacher name="Marcelo"></Teacher><Subject name="Quimica"></Subject>
    </Hour>
    <Hour name="2">
      <Teacher name="Aparacida"></Teacher><Subject name="Geografia"></Subject>
    </Hour>
    <Hour name="3">
      <Teacher name="Luzia"></Teacher><Subject name="Lingua Portuguesa"></Subject>
    </Hour>
    <Hour name="4">
      <Teacher name="Wellington"></Teacher><Subject name="Matematica"></Subject>
    </Hour>
   </Day>
   <Day name="Marti">
    <Hour name="0">
      <Teacher name="Luzia"></Teacher><Subject name="Lingua Portuguesa"></Subject>
    </Hour>
    <Hour name="1">
      <Teacher name="Silvana"></Teacher><Subject name="Ingles"></Subject>
    </Hour>
    <Hour name="2">
      <Teacher name="Carla"></Teacher><Subject name="Artes"></Subject>
    </Hour>
    <Hour name="3">
      <Teacher name="Marcelo"></Teacher><Subject name="Quimica"></Subject>
    </Hour>
    <Hour name="4">
      <Teacher name="Anderson"></Teacher><Subject name="Educcacao Fisica"></Subject>
    </Hour>
   </Day>
   <Day name="Miercuri">
    <Hour name="0">
      <Teacher name="Andreia2"></Teacher><Subject name="Fisica"></Subject>
    </Hour>
    <Hour name="1">
      <Teacher name="Luzia"></Teacher><Subject name="Lingua Portuguesa"></Subject>
    </Hour>
    <Hour name="2">
      <Teacher name="Marli"></Teacher><Subject name="Historia"></Subject>
    </Hour>
    <Hour name="3">
      <Teacher name="Aparacida"></Teacher><Subject name="Geografia"></Subject>
    </Hour>
    <Hour name="4">
      <Teacher name="Osvaldo"></Teacher><Subject name="Biologia"></Subject>
    </Hour>
   </Day>
   <Day name="Joi">
    <Hour name="0">
      <Teacher name="Andreia2"></Teacher><Subject name="Fisica"></Subject>
    </Hour>
    <Hour name="1">
      <Teacher name="Roberto"></Teacher><Subject name="Sociologia"></Subject>
    </Hour>
    <Hour name="2">
      <Teacher name="Wellington"></Teacher><Subject name="Matematica"></Subject>
    </Hour>
    <Hour name="3">
      <Teacher name="Aparacida"></Teacher><Subject name="Geografia"></Subject>
    </Hour>
    <Hour name="4">
      <Teacher name="Marli"></Teacher><Subject name="Historia"></Subject>
    </Hour>
   </Day>
   <Day name="Vineri">
    <Hour name="0">
      <Teacher name="Osvaldo"></Teacher><Subject name="Biologia"></Subject>
    </Hour>
    <Hour name="1">
      <Teacher name="Roberto"></Teacher><Subject name="Sociologia"></Subject>
    </Hour>
    <Hour name="2">
      <Teacher name="Luzia"></Teacher><Subject name="Lingua Portuguesa"></Subject>
    </Hour>
    <Hour name="3">
      <Teacher name="Wellington"></Teacher><Subject name="Matematica"></Subject>
    </Hour>
    <Hour name="4">
      <Teacher name="Silvana"></Teacher><Subject name="Ingles"></Subject>
    </Hour>
   </Day>
  </Subgroup>
  <Subgroup name="305 Grupo Automático Subgrupo Automático">
   <Day name="Luni">
    <Hour name="0">
      <Teacher name="Wellington"></Teacher><Subject name="Matematica"></Subject>
    </Hour>
    <Hour name="1">
      <Teacher name="Luzia"></Teacher><Subject name="Lingua Portuguesa"></Subject>
    </Hour>
    <Hour name="2">
      <Teacher name="Marli"></Teacher><Subject name="Historia"></Subject>
    </Hour>
    <Hour name="3">
      <Teacher name="Viviane"></Teacher><Subject name="Geografia"></Subject>
    </Hour>
    <Hour name="4">
      <Teacher name="Anderson"></Teacher><Subject name="Educcacao Fisica"></Subject>
    </Hour>
   </Day>
   <Day name="Marti">
    <Hour name="0">
      <Teacher name="Anderson"></Teacher><Subject name="Educcacao Fisica"></Subject>
    </Hour>
    <Hour name="1">
      <Teacher name="Wellington"></Teacher><Subject name="Matematica"></Subject>
    </Hour>
    <Hour name="2">
      <Teacher name="Luzia"></Teacher><Subject name="Lingua Portuguesa"></Subject>
    </Hour>
    <Hour name="3">
      <Teacher name="Carla"></Teacher><Subject name="Artes"></Subject>
    </Hour>
    <Hour name="4">
      <Teacher name="Silvana"></Teacher><Subject name="Ingles"></Subject>
    </Hour>
   </Day>
   <Day name="Miercuri">
    <Hour name="0">
      <Teacher name="Osvaldo"></Teacher><Subject name="Biologia"></Subject>
    </Hour>
    <Hour name="1">
      <Teacher name="Andreia2"></Teacher><Subject name="Fisica"></Subject>
    </Hour>
    <Hour name="2">
      <Teacher name="Luzia"></Teacher><Subject name="Lingua Portuguesa"></Subject>
    </Hour>
    <Hour name="3">
      <Teacher name="Silvana"></Teacher><Subject name="Ingles"></Subject>
    </Hour>
    <Hour name="4">
      <Teacher name="Marcelo"></Teacher><Subject name="Quimica"></Subject>
    </Hour>
   </Day>
   <Day name="Joi">
    <Hour name="0">
      <Teacher name="Marli"></Teacher><Subject name="Historia"></Subject>
    </Hour>
    <Hour name="1">
      <Teacher name="Wellington"></Teacher><Subject name="Matematica"></Subject>
    </Hour>
    <Hour name="2">
      <Teacher name="Marcelo"></Teacher><Subject name="Quimica"></Subject>
    </Hour>
    <Hour name="3">
      <Teacher name="Roberto"></Teacher><Subject name="Sociologia"></Subject>
    </Hour>
    <Hour name="4">
      <Teacher name="Viviane"></Teacher><Subject name="Geografia"></Subject>
    </Hour>
   </Day>
   <Day name="Vineri">
    <Hour name="0">
      <Teacher name="Viviane"></Teacher><Subject name="Geografia"></Subject>
    </Hour>
    <Hour name="1">
      <Teacher name="Osvaldo"></Teacher><Subject name="Biologia"></Subject>
    </Hour>
    <Hour name="2">
      <Teacher name="Roberto"></Teacher><Subject name="Sociologia"></Subject>
    </Hour>
    <Hour name="3">
      <Teacher name="Luzia"></Teacher><Subject name="Lingua Portuguesa"></Subject>
    </Hour>
    <Hour name="4">
      <Teacher name="Andreia2"></Teacher><Subject name="Fisica"></Subject>
    </Hour>
   </Day>
  </Subgroup>
</Students_Timetable>
